algosquare/__init__.py
algosquare/api/__init__.py
algosquare/api/algo.py
algosquare/api/api.py
algosquare/api/common.py
algosquare/api/dataset.py
algosquare/api/model.py
algosquare/api/package.py
algosquare/api/predictor.py
algosquare/api/task.py
algosquare/base/__init__.py
algosquare/base/algo.py
algosquare/base/errors.py
algosquare/base/metric.py
algosquare/base/predictor.py
algosquare/base/tabular.py
algosquare/base/types.py
algosquare/metrics/__init__.py
algosquare/metrics/metrics.py
algosquare/platform/__init__.py
algosquare/platform/tabular.py
algosquare/testing/__init__.py
algosquare/testing/algo.py
algosquare/testing/errors.py
algosquare/testing/metric.py
algosquare/testing/tabular.py
algosquare/testing/targets.py
algosquare/tools/__init__.py
algosquare/tools/analytics.py
algosquare/tools/transformers.py
algosquare-0.0.110.dist-info/LICENSE
algosquare-0.0.110.dist-info/METADATA
algosquare-0.0.110.dist-info/WHEEL
algosquare-0.0.110.dist-info/top_level.txt
algosquare-0.0.110.dist-info/RECORD
