Metadata-Version: 2.1
Name: algosquare
Version: 0.0.110
Summary: Library for interfacing with algosquare.ai
Home-page: https://www.algosquare.ai
Author: AlgoSquare contributers
Author-email: contact@algosquare.ai
License: MIT License
Keywords: algosquare,tools,api
Platform: UNKNOWN
Classifier: Programming Language :: Python :: 3
Classifier: License :: OSI Approved :: MIT License
Classifier: Operating System :: OS Independent
License-File: LICENSE
Provides-Extra: full
Requires-Dist: requests ; extra == 'full'
Requires-Dist: numpy ; extra == 'full'
Requires-Dist: scikit-learn ; extra == 'full'
Requires-Dist: pandas ; extra == 'full'
